Struts2KuangjiaRumenjiaochengCYuyanBianchengWang/README.md
Struts2KuangjiaRumenjiaochengCYuyanBianchengWang/__init__.py
Struts2KuangjiaRumenjiaochengCYuyanBianchengWang/__main__.py
Struts2KuangjiaRumenjiaochengCYuyanBianchengWang/file.epub
Struts2KuangjiaRumenjiaochengCYuyanBianchengWang/index.html
Struts2KuangjiaRumenjiaochengCYuyanBianchengWang/css/__init__.py
Struts2KuangjiaRumenjiaochengCYuyanBianchengWang/css/annotations.css
Struts2KuangjiaRumenjiaochengCYuyanBianchengWang/css/main.css
Struts2KuangjiaRumenjiaochengCYuyanBianchengWang/css/normalize.css
Struts2KuangjiaRumenjiaochengCYuyanBianchengWang/css/popup.css
Struts2KuangjiaRumenjiaochengCYuyanBianchengWang/font/__init__.py
Struts2KuangjiaRumenjiaochengCYuyanBianchengWang/font/fontello.eot
Struts2KuangjiaRumenjiaochengCYuyanBianchengWang/font/fontello.svg
Struts2KuangjiaRumenjiaochengCYuyanBianchengWang/font/fontello.ttf
Struts2KuangjiaRumenjiaochengCYuyanBianchengWang/font/fontello.woff
Struts2KuangjiaRumenjiaochengCYuyanBianchengWang/img/__init__.py
Struts2KuangjiaRumenjiaochengCYuyanBianchengWang/img/annotator-glyph-sprite.png
Struts2KuangjiaRumenjiaochengCYuyanBianchengWang/img/annotator-icon-sprite.png
Struts2KuangjiaRumenjiaochengCYuyanBianchengWang/img/apple-touch-icon.png
Struts2KuangjiaRumenjiaochengCYuyanBianchengWang/img/cancelfullscreen.png
Struts2KuangjiaRumenjiaochengCYuyanBianchengWang/img/close.png
Struts2KuangjiaRumenjiaochengCYuyanBianchengWang/img/fullscreen.png
Struts2KuangjiaRumenjiaochengCYuyanBianchengWang/img/loader.gif
Struts2KuangjiaRumenjiaochengCYuyanBianchengWang/img/menu-icon.png
Struts2KuangjiaRumenjiaochengCYuyanBianchengWang/img/save.png
Struts2KuangjiaRumenjiaochengCYuyanBianchengWang/img/saved.png
Struts2KuangjiaRumenjiaochengCYuyanBianchengWang/img/settings-s.png
Struts2KuangjiaRumenjiaochengCYuyanBianchengWang/img/settings.png
Struts2KuangjiaRumenjiaochengCYuyanBianchengWang/img/star.png
Struts2KuangjiaRumenjiaochengCYuyanBianchengWang/js/__init__.py
struts2_kuangjia_rumenjiaocheng_c_yuyan_biancheng_wang-2024.3.5.0.dist-info/METADATA
struts2_kuangjia_rumenjiaocheng_c_yuyan_biancheng_wang-2024.3.5.0.dist-info/WHEEL
struts2_kuangjia_rumenjiaocheng_c_yuyan_biancheng_wang-2024.3.5.0.dist-info/entry_points.txt
struts2_kuangjia_rumenjiaocheng_c_yuyan_biancheng_wang-2024.3.5.0.dist-info/top_level.txt
struts2_kuangjia_rumenjiaocheng_c_yuyan_biancheng_wang-2024.3.5.0.dist-info/RECORD
